main.py
src/converter_sulfin/__init__.py
src/converter_sulfin/converter.py
sulfin_binary_converter-0.0.4.dist-info/METADATA
sulfin_binary_converter-0.0.4.dist-info/WHEEL
sulfin_binary_converter-0.0.4.dist-info/licenses/LICENSE
sulfin_binary_converter-0.0.4.dist-info/RECORD
