Metadata-Version: 2.1
Name: sulfin-binary-converter
Version: 0.0.4
Summary: A bi-directional binary decimal converter
Author-email: sulfin <sulfin83@gmail.com>
License-File: LICENSE
Classifier: License :: OSI Approved :: MIT License
Classifier: Operating System :: OS Independent
Classifier: Programming Language :: Python :: 3
Requires-Python: >=3.7
